pyupdater/__init__.py
pyupdater/__main__.py
pyupdater/_version.py
pyupdater/settings.py
pyupdater/cli/__init__.py
pyupdater/cli/commands.py
pyupdater/cli/helpers.py
pyupdater/cli/options.py
pyupdater/client/__init__.py
pyupdater/client/downloader.py
pyupdater/client/patcher.py
pyupdater/client/updates.py
pyupdater/core/__init__.py
pyupdater/core/uploader.py
pyupdater/core/key_handler/__init__.py
pyupdater/core/key_handler/keys.py
pyupdater/core/package_handler/__init__.py
pyupdater/core/package_handler/package.py
pyupdater/core/package_handler/patch.py
pyupdater/hooks/__init__.py
pyupdater/hooks/hook-dsdev_utils.py
pyupdater/utils/__init__.py
pyupdater/utils/builder.py
pyupdater/utils/compat.py
pyupdater/utils/config.py
pyupdater/utils/exceptions.py
pyupdater/utils/pyinstaller_compat.py
pyupdater/utils/storage.py
PyUpdater-3.1.1.dist-info/METADATA
PyUpdater-3.1.1.dist-info/WHEEL
PyUpdater-3.1.1.dist-info/entry_points.txt
PyUpdater-3.1.1.dist-info/top_level.txt
PyUpdater-3.1.1.dist-info/RECORD
